Metadata-Version: 1.1
Name: bejjoeqq
Version: 1.4
Summary: Beta Version
Home-page: UNKNOWN
Author: Aldhiya Rozak
Author-email: Aldhiya.rozak@gmail.com
License: MIT
Keywords: Random Library
Platform: UNKNOWN
Classifier: Development Status :: 5 - Production/Stable
Classifier: Intended Audience :: Education
Classifier: Operating System :: Microsoft :: Windows :: Windows 10
Classifier: License :: OSI Approved :: MIT License
Classifier: Programming Language :: Python :: 3
